docs/source/conf.py
examples/example_hatp22.py
examples/example_hatp4.py
examples/example_wasp12.py
examples/test.py
orbdot/__init__.py
orbdot/analysis.py
orbdot/joint_fit.py
orbdot/light_travel_time.py
orbdot/nested_sampling.py
orbdot/radial_velocity.py
orbdot/star_planet.py
orbdot/transit_duration.py
orbdot/transit_timing.py
orbdot/defaults/__init__.py
orbdot/defaults/default_info_file.json
orbdot/defaults/default_plot_settings.json
orbdot/defaults/default_settings_file.json
orbdot/models/__init__.py
orbdot/models/ltt_models.py
orbdot/models/rv_models.py
orbdot/models/tdv_models.py
orbdot/models/theory.py
orbdot/models/ttv_models.py
orbdot/tools/__init__.py
orbdot/tools/plots.py
orbdot/tools/priors.py
orbdot/tools/stats.py
orbdot/tools/utilities.py
orbdot-1.0.0.dist-info/licenses/LICENSE
tests/test_decay.py
tests/test_rv.py
orbdot-1.0.0.dist-info/METADATA
orbdot-1.0.0.dist-info/WHEEL
orbdot-1.0.0.dist-info/top_level.txt
orbdot-1.0.0.dist-info/RECORD
