Metadata-Version: 2.4
Name: orbdot
Version: 1.0.0
Summary: A Python package for studying secular evolution of exoplanet orbits using observational data.
Author-email: "Simone R. Hagey" <shagey@phas.ubc.ca>, "Aaron C. Boley" <acboley@phas.ubc.ca>
Maintainer-email: "Simone R. Hagey" <shagey@phas.ubc.ca>
License: MIT License
Project-URL: Source, https://github.com/simonehagey/orbdot
Project-URL: Documentation, https://orbdot.readthedocs.io/en/latest/
Classifier: Programming Language :: Python :: 3
Classifier: Programming Language :: Python :: 3.9
Classifier: Programming Language :: Python :: 3.10
Classifier: Programming Language :: Python :: 3.11
Classifier: Programming Language :: Python :: 3.12
Classifier: Programming Language :: Python :: 3.13
Classifier: License :: OSI Approved :: MIT License
Classifier: Operating System :: Unix
Classifier: Operating System :: MacOS
Classifier: Development Status :: 5 - Production/Stable
Classifier: Intended Audience :: Science/Research
Classifier: Natural Language :: English
Classifier: Topic :: Scientific/Engineering :: Astronomy
Requires-Python: >=3.9
License-File: LICENSE
Requires-Dist: astropy>=5.1.1
Requires-Dist: corner>=2.2.1
Requires-Dist: matplotlib>=3.6.0
Requires-Dist: nestle>=0.2.0
Requires-Dist: numpy>=1.24.0
Requires-Dist: scipy>=1.13.0
Provides-Extra: docs
Requires-Dist: sphinx>=7.1.2; extra == "docs"
Requires-Dist: sphinx_rtd_theme>=2; extra == "docs"
Requires-Dist: docutils>=0.18.1; extra == "docs"
Requires-Dist: sphinx-copybutton; extra == "docs"
Requires-Dist: sphinx-togglebutton; extra == "docs"
Requires-Dist: sphinxcontrib-bibtex; extra == "docs"
Requires-Dist: sphinx-autodoc-typehints; extra == "docs"
Requires-Dist: numpydoc; extra == "docs"
Provides-Extra: test
Requires-Dist: pytest; extra == "test"
Requires-Dist: pytest-cov; extra == "test"
Dynamic: license-file
